splent/__init__.py
splent-0.0.1.dist-info/METADATA
splent-0.0.1.dist-info/WHEEL
splent-0.0.1.dist-info/top_level.txt
splent-0.0.1.dist-info/RECORD
