Metadata-Version: 2.2
Name: splent
Version: 0.0.1
Summary: SPLENT sample package
Author-email: David Romero <drorganvidez@us.es>
Classifier: Programming Language :: Python :: 3
Classifier: License :: OSI Approved :: MIT License
Classifier: Operating System :: OS Independent
Requires-Python: >=3.12
